memsparkline/__init__.py
memsparkline/__main__.py
memsparkline/main.py
memsparkline/py.typed
memsparkline-0.6.0.dist-info/LICENSE
memsparkline-0.6.0.dist-info/METADATA
memsparkline-0.6.0.dist-info/WHEEL
memsparkline-0.6.0.dist-info/entry_points.txt
memsparkline-0.6.0.dist-info/RECORD
