Metadata-Version: 2.1
Name: memsparkline
Version: 0.6.0
Summary: Track the RAM usage (resident set size) of a process and its descendants in real time.
Home-page: https://github.com/dbohdan/memsparkline
License: MIT
Keywords: memory,monitoring,performance,RAM,resident set size,sparklines
Author: D. Bohdan
Author-email: dbohdan@dbohdan.com
Requires-Python: >=3.8,<4.0
Classifier: Development Status :: 4 - Beta
Classifier: Environment :: Console
Classifier: License :: OSI Approved :: MIT License
Classifier: Operating System :: MacOS :: MacOS X
Classifier: Operating System :: Microsoft :: Windows
Classifier: Operating System :: POSIX
Classifier: Programming Language :: Python :: 3
Classifier: Programming Language :: Python :: 3.8
Classifier: Programming Language :: Python :: 3.9
Classifier: Programming Language :: Python :: 3.10
Classifier: Programming Language :: Python :: 3.11
Classifier: Programming Language :: Python :: 3.12
Classifier: Topic :: System :: Benchmark
Classifier: Topic :: System :: Monitoring
Classifier: Topic :: Utilities
Requires-Dist: psutil (>=5.9.5,<6.0.0)
Project-URL: Repository, https://github.com/dbohdan/memsparkline
